py_irstd_metrics/__init__.py
py_irstd_metrics/pixelwise_metrics.py
py_irstd_metrics/targetwise_metrics.py
py_irstd_metrics/utils.py
pyirstdmetrics-1.0.1.dist-info/licenses/LICENSE.txt
pyirstdmetrics-1.0.1.dist-info/METADATA
pyirstdmetrics-1.0.1.dist-info/WHEEL
pyirstdmetrics-1.0.1.dist-info/top_level.txt
pyirstdmetrics-1.0.1.dist-info/RECORD
