Metadata-Version: 2.4
Name: pyirstdmetrics
Version: 1.0.1
Summary: A simple and efficient implementation for the IRSTD performance analysis.
Author-email: lartpang <lartpang@gmail.com>
Maintainer-email: lartpang <lartpang@gmail.com>
License: MIT License
Project-URL: Homepage, https://github.com/lartpang/PyIRSTDMetrics
Project-URL: Documentation, https://github.com/lartpang/PyIRSTDMetrics
Project-URL: Repository, https://github.com/lartpang/PyIRSTDMetrics.git
Project-URL: Bug Tracker, https://github.com/lartpang/PyIRSTDMetrics/issues
Project-URL: Changelog, https://github.com/lartpang/PyIRSTDMetrics/blob/master/CHANGELOG.md
Keywords: infrared small target detection,infrared small target segmentation,evaluation,metric,deep learning
Classifier: Development Status :: 5 - Production/Stable
Classifier: Environment :: Console
Classifier: Intended Audience :: Developers
Classifier: Operating System :: OS Independent
Classifier: Programming Language :: Python
Classifier: Topic :: Scientific/Engineering :: Artificial Intelligence
Requires-Python: >=3.6
License-File: LICENSE.txt
Requires-Dist: numpy<2.0,>=1.23
Requires-Dist: scikit-image<1.0,>=0.14.1
Requires-Dist: scipy<2.0,>=1.10
Dynamic: license-file
